rvrbase/__about__.py
rvrbase/__init__.py
rvrbase/constants.py
rvrbase/rvrbase.py
rvrbase/api/__init__.py
rvrbase/api/azure_logger_api.py
rvrbase/api/azure_reader_api.py
rvrbase/api/notification_api.py
rvrbase/api/rvrconfig.py
test/__init__.py
test/test_azure_reader_api.py
test/test_delegate.py
rvr_base-1.1.1.dist-info/LICENSE
rvr_base-1.1.1.dist-info/METADATA
rvr_base-1.1.1.dist-info/WHEEL
rvr_base-1.1.1.dist-info/top_level.txt
rvr_base-1.1.1.dist-info/RECORD
