Metadata-Version: 2.1
Name: rvr-base
Version: 1.1.1
Summary: Roberts base module
Home-page: https://github.com/robertreems/rvrbase
Author: Robert van Reems
Classifier: Programming Language :: Python :: 3
Classifier: License :: OSI Approved :: MIT License
Classifier: Operating System :: POSIX :: Linux
Requires-Python: >=3.8
License-File: LICENSE
Requires-Dist: dbus-python
Requires-Dist: notify-run
